satus_sdk/Job.py
satus_sdk/JobOptions.py
satus_sdk/ReturnTypes.py
satus_sdk/SatusClient.py
satus_sdk/__init__.py
satus_sdk/utils.py
satus_sdk-0.1.0.dist-info/LICENSE
satus_sdk-0.1.0.dist-info/METADATA
satus_sdk-0.1.0.dist-info/WHEEL
satus_sdk-0.1.0.dist-info/top_level.txt
satus_sdk-0.1.0.dist-info/RECORD
