Metadata-Version: 2.1
Name: satus-sdk
Version: 0.1.0
Summary: A python wrapper for the satus.dev API
Home-page: https://satus.dev
Author: Jonas Briguet
Author-email: briguetjo@yahoo.de
Project-URL: Homepage, https://www.satus.dev
Keywords: transcription,audio,video,speech,satus,api,wrapper
Classifier: Programming Language :: Python :: 3
Classifier: License :: OSI Approved :: MIT License
Classifier: Operating System :: OS Independent
Requires-Python: >=3.8
License-File: LICENSE
Requires-Dist: requests
Requires-Dist: requests-toolbelt
Requires-Dist: urllib3
